[
  {
    "ContainingType": "Autonomus.Controllers.ComentarioController",
    "Method": "Get",
    "RelativePath": "api/Comentario",
    "HttpMethod": "GET",
    "IsController": true,
    "Order": 0,
    "Parameters": [],
    "ReturnTypes": [
      {
        "Type": "System.Collections.Generic.List\u00601[[Autonomus.ContextNameSpace.comentario_Cliente, Autonomus, Version=1.0.0.0, Culture=neutral, PublicKeyToken=null]]",
        "MediaTypes": [
          "text/plain",
          "application/json",
          "text/json"
        ],
        "StatusCode": 200
      }
    ]
  },
  {
    "ContainingType": "Autonomus.Controllers.ComentarioController",
    "Method": "Post",
    "RelativePath": "api/Comentario",
    "HttpMethod": "POST",
    "IsController": true,
    "Order": 0,
    "Parameters": [
      {
        "Name": "comentario",
        "Type": "Autonomus.ContextNameSpace.comentario_Cliente",
        "IsRequired": true
      }
    ],
    "ReturnTypes": []
  },
  {
    "ContainingType": "Autonomus.Controllers.ComentarioController",
    "Method": "Delete",
    "RelativePath": "api/Comentario/{id}",
    "HttpMethod": "DELETE",
    "IsController": true,
    "Order": 0,
    "Parameters": [
      {
        "Name": "id_comentario_cliente",
        "Type": "System.Int32",
        "IsRequired": false
      },
      {
        "Name": "id",
        "Type": "",
        "IsRequired": true
      }
    ],
    "ReturnTypes": [
      {
        "Type": "System.Void",
        "MediaTypes": [],
        "StatusCode": 200
      }
    ]
  },
  {
    "ContainingType": "Autonomus.Controllers.ComentarioPrestadorController",
    "Method": "Get",
    "RelativePath": "api/ComentarioPrestador",
    "HttpMethod": "GET",
    "IsController": true,
    "Order": 0,
    "Parameters": [],
    "ReturnTypes": [
      {
        "Type": "System.Collections.Generic.List\u00601[[Autonomus.ContextNameSpace.comentario_Prestador, Autonomus, Version=1.0.0.0, Culture=neutral, PublicKeyToken=null]]",
        "MediaTypes": [
          "text/plain",
          "application/json",
          "text/json"
        ],
        "StatusCode": 200
      }
    ]
  },
  {
    "ContainingType": "Autonomus.Controllers.ComentarioPrestadorController",
    "Method": "Post",
    "RelativePath": "api/ComentarioPrestador",
    "HttpMethod": "POST",
    "IsController": true,
    "Order": 0,
    "Parameters": [
      {
        "Name": "comentario",
        "Type": "Autonomus.ContextNameSpace.comentario_Prestador",
        "IsRequired": true
      }
    ],
    "ReturnTypes": []
  },
  {
    "ContainingType": "Autonomus.Controllers.ComentarioPrestadorController",
    "Method": "Delete",
    "RelativePath": "api/ComentarioPrestador/{id}",
    "HttpMethod": "DELETE",
    "IsController": true,
    "Order": 0,
    "Parameters": [
      {
        "Name": "id",
        "Type": "System.Int32",
        "IsRequired": true
      }
    ],
    "ReturnTypes": []
  },
  {
    "ContainingType": "Autonomus.Controllers.ClienteController",
    "Method": "Get",
    "RelativePath": "Cliente",
    "HttpMethod": "GET",
    "IsController": true,
    "Order": 0,
    "Parameters": [],
    "ReturnTypes": [
      {
        "Type": "System.Collections.Generic.List\u00601[[Autonomus.Entities.Cliente, Autonomus, Version=1.0.0.0, Culture=neutral, PublicKeyToken=null]]",
        "MediaTypes": [
          "text/plain",
          "application/json",
          "text/json"
        ],
        "StatusCode": 200
      }
    ]
  },
  {
    "ContainingType": "Autonomus.Controllers.ClienteController",
    "Method": "Post",
    "RelativePath": "Cliente",
    "HttpMethod": "POST",
    "IsController": true,
    "Order": 0,
    "Parameters": [
      {
        "Name": "cliente",
        "Type": "Autonomus.Entities.Cliente",
        "IsRequired": true
      }
    ],
    "ReturnTypes": [
      {
        "Type": "System.Decimal",
        "MediaTypes": [
          "text/plain",
          "application/json",
          "text/json"
        ],
        "StatusCode": 200
      }
    ]
  },
  {
    "ContainingType": "Autonomus.Controllers.ClienteController",
    "Method": "Delete",
    "RelativePath": "Cliente",
    "HttpMethod": "DELETE",
    "IsController": true,
    "Order": 0,
    "Parameters": [
      {
        "Name": "idCliente",
        "Type": "System.Int32",
        "IsRequired": false
      }
    ],
    "ReturnTypes": [
      {
        "Type": "System.Void",
        "MediaTypes": [],
        "StatusCode": 200
      }
    ]
  },
  {
    "ContainingType": "Autonomus.Controllers.ClienteController",
    "Method": "Put",
    "RelativePath": "Cliente",
    "HttpMethod": "PUT",
    "IsController": true,
    "Order": 0,
    "Parameters": [
      {
        "Name": "cliente",
        "Type": "Autonomus.Entities.Cliente",
        "IsRequired": true
      }
    ],
    "ReturnTypes": [
      {
        "Type": "System.Void",
        "MediaTypes": [],
        "StatusCode": 200
      }
    ]
  },
  {
    "ContainingType": "Autonomus.Controllers.ClienteController",
    "Method": "Filtrar",
    "RelativePath": "Cliente/filtrar",
    "HttpMethod": "GET",
    "IsController": true,
    "Order": 0,
    "Parameters": [
      {
        "Name": "nome",
        "Type": "System.String",
        "IsRequired": false
      }
    ],
    "ReturnTypes": [
      {
        "Type": "System.Collections.Generic.List\u00601[[Autonomus.Entities.Cliente, Autonomus, Version=1.0.0.0, Culture=neutral, PublicKeyToken=null]]",
        "MediaTypes": [
          "text/plain",
          "application/json",
          "text/json"
        ],
        "StatusCode": 200
      }
    ]
  },
  {
    "ContainingType": "Autonomus.Controllers.ClienteController",
    "Method": "FiltrarPorCidade",
    "RelativePath": "Cliente/filtrar-por-cidade",
    "HttpMethod": "GET",
    "IsController": true,
    "Order": 0,
    "Parameters": [
      {
        "Name": "cidade",
        "Type": "System.String",
        "IsRequired": false
      }
    ],
    "ReturnTypes": [
      {
        "Type": "System.Collections.Generic.List\u00601[[Autonomus.Entities.Cliente, Autonomus, Version=1.0.0.0, Culture=neutral, PublicKeyToken=null]]",
        "MediaTypes": [
          "text/plain",
          "application/json",
          "text/json"
        ],
        "StatusCode": 200
      }
    ]
  },
  {
    "ContainingType": "Autonomus.Controllers.ClienteFiltroController",
    "Method": "GetObterClientesPorRating",
    "RelativePath": "ClienteFiltro",
    "HttpMethod": "GET",
    "IsController": true,
    "Order": 0,
    "Parameters": [
      {
        "Name": "avaliacaominima",
        "Type": "System.Decimal",
        "IsRequired": false
      },
      {
        "Name": "avaliacaomaxima",
        "Type": "System.Decimal",
        "IsRequired": false
      }
    ],
    "ReturnTypes": [
      {
        "Type": "System.Collections.Generic.List\u00601[[Autonomus.Entities.Cliente, Autonomus, Version=1.0.0.0, Culture=neutral, PublicKeyToken=null]]",
        "MediaTypes": [
          "text/plain",
          "application/json",
          "text/json"
        ],
        "StatusCode": 200
      }
    ]
  },
  {
    "ContainingType": "Autonomus.Controllers.PrestadorController",
    "Method": "Get",
    "RelativePath": "Prestador",
    "HttpMethod": "GET",
    "IsController": true,
    "Order": 0,
    "Parameters": [],
    "ReturnTypes": [
      {
        "Type": "System.Collections.Generic.List\u00601[[Autonomus.Entities.Prestador, Autonomus, Version=1.0.0.0, Culture=neutral, PublicKeyToken=null]]",
        "MediaTypes": [
          "text/plain",
          "application/json",
          "text/json"
        ],
        "StatusCode": 200
      }
    ]
  },
  {
    "ContainingType": "Autonomus.Controllers.PrestadorController",
    "Method": "Post",
    "RelativePath": "Prestador",
    "HttpMethod": "POST",
    "IsController": true,
    "Order": 0,
    "Parameters": [
      {
        "Name": "prestador",
        "Type": "Autonomus.Entities.Prestador",
        "IsRequired": true
      }
    ],
    "ReturnTypes": [
      {
        "Type": "System.Decimal",
        "MediaTypes": [
          "text/plain",
          "application/json",
          "text/json"
        ],
        "StatusCode": 200
      }
    ]
  },
  {
    "ContainingType": "Autonomus.Controllers.PrestadorController",
    "Method": "Delete",
    "RelativePath": "Prestador",
    "HttpMethod": "DELETE",
    "IsController": true,
    "Order": 0,
    "Parameters": [
      {
        "Name": "idPrestador",
        "Type": "System.Int32",
        "IsRequired": false
      }
    ],
    "ReturnTypes": [
      {
        "Type": "System.Void",
        "MediaTypes": [],
        "StatusCode": 200
      }
    ]
  },
  {
    "ContainingType": "Autonomus.Controllers.PrestadorController",
    "Method": "Put",
    "RelativePath": "Prestador",
    "HttpMethod": "PUT",
    "IsController": true,
    "Order": 0,
    "Parameters": [
      {
        "Name": "prestador",
        "Type": "Autonomus.Entities.Prestador",
        "IsRequired": true
      }
    ],
    "ReturnTypes": [
      {
        "Type": "System.Void",
        "MediaTypes": [],
        "StatusCode": 200
      }
    ]
  },
  {
    "ContainingType": "Autonomus.Controllers.PrestadorController",
    "Method": "Filtrar",
    "RelativePath": "Prestador/filtrar",
    "HttpMethod": "GET",
    "IsController": true,
    "Order": 0,
    "Parameters": [
      {
        "Name": "nome",
        "Type": "System.String",
        "IsRequired": false
      }
    ],
    "ReturnTypes": [
      {
        "Type": "System.Collections.Generic.List\u00601[[Autonomus.Entities.Prestador, Autonomus, Version=1.0.0.0, Culture=neutral, PublicKeyToken=null]]",
        "MediaTypes": [
          "text/plain",
          "application/json",
          "text/json"
        ],
        "StatusCode": 200
      }
    ]
  },
  {
    "ContainingType": "Autonomus.Controllers.PrestadorController",
    "Method": "FiltrarPorCidade",
    "RelativePath": "Prestador/filtrar-por-cidade--prestador",
    "HttpMethod": "GET",
    "IsController": true,
    "Order": 0,
    "Parameters": [
      {
        "Name": "cidade",
        "Type": "System.String",
        "IsRequired": false
      }
    ],
    "ReturnTypes": [
      {
        "Type": "System.Collections.Generic.List\u00601[[Autonomus.Entities.Prestador, Autonomus, Version=1.0.0.0, Culture=neutral, PublicKeyToken=null]]",
        "MediaTypes": [
          "text/plain",
          "application/json",
          "text/json"
        ],
        "StatusCode": 200
      }
    ]
  },
  {
    "ContainingType": "Autonomus.Controllers.WeatherForecastController",
    "Method": "Get",
    "RelativePath": "WeatherForecast",
    "HttpMethod": "GET",
    "IsController": true,
    "Order": 0,
    "Parameters": [],
    "ReturnTypes": [
      {
        "Type": "System.Collections.Generic.IEnumerable\u00601[[Autonomus.WeatherForecast, Autonomus, Version=1.0.0.0, Culture=neutral, PublicKeyToken=null]]",
        "MediaTypes": [
          "text/plain",
          "application/json",
          "text/json"
        ],
        "StatusCode": 200
      }
    ]
  }
]